src/__init__.py
src/pipeline/__init__.py
src/pipeline/config.py
src/pipeline/constants.py
src/pipeline/paths.py
src/pipeline/pipeline_manager.py
src/pipeline/utils.py
src/pipeline/data_drift_detection/__init__.py
src/pipeline/data_drift_detection/constants.py
src/pipeline/data_drift_detection/data_drift.py
src/pipeline/data_drift_detection/data_drift_detection_manager.py
src/pipeline/data_drift_detection/detectors/__init__.py
src/pipeline/data_drift_detection/detectors/data_drift_detector.py
src/pipeline/data_drift_detection/detectors/model_based_detector.py
src/pipeline/data_drift_detection/detectors/scikit_multiflow_data_drift_detector.py
src/pipeline/data_drift_detection/detectors/statistical_based_detector.py
src/pipeline/data_drift_detection/detectors/tensorflow_data_drift_detector.py
src/pipeline/data_drift_detection/interfaces/__init__.py
src/pipeline/data_drift_detection/interfaces/idata_drift_detector.py
src/pipeline/data_generation/__init__.py
src/pipeline/data_generation/data_generation_manager.py
src/pipeline/data_generation/data_generator.py
src/pipeline/data_generation/interfaces/__init__.py
src/pipeline/data_generation/interfaces/idata_generator.py
src/pipeline/data_generation/raw_files/__init__.py
src/pipeline/datasets/__init__.py
src/pipeline/datasets/constants.py
src/pipeline/datasets/dataset.py
src/pipeline/datasets/deployment_datasets.py
src/pipeline/datasets/paths.py
src/pipeline/datasets/training_datasets.py
src/pipeline/evaluation/__init__.py
src/pipeline/evaluation/evaluation_manager.py
src/pipeline/interfaces/__init__.py
src/pipeline/interfaces/imanager.py
src/pipeline/logger/__init__.py
src/pipeline/logger/logger.py
src/pipeline/model/__init__.py
src/pipeline/model/constants.py
src/pipeline/model/data_drift_models.py
src/pipeline/model/model_metrics.py
src/pipeline/model/model_trainining_manager.py
src/pipeline/model/paths.py
src/pipeline/model/production_models.py
src/pipeline/model/interfaces/__init__.py
data_drift_detection-1.0.0.dist-info/LICENSE
data_drift_detection-1.0.0.dist-info/METADATA
data_drift_detection-1.0.0.dist-info/WHEEL
data_drift_detection-1.0.0.dist-info/entry_points.txt
data_drift_detection-1.0.0.dist-info/top_level.txt
data_drift_detection-1.0.0.dist-info/RECORD
